Metadata-Version: 2.1
Name: ru_parser_cv
Version: 1.0.1
Summary: Python module for parsing Russian CVs and extracting information from them
Home-page: https://github.com/dmitry-batrov/ru_parser_cv
Author: Dmitry Batrov
Author-email: d.batrov@yandex.ru
License: Apache License, Version 2.0
Classifier: License :: OSI Approved :: Apache Software License
Classifier: Operating System :: OS Independent
Classifier: Programming Language :: Python :: 3.6
Requires-Python: >=3.6
License-File: LICENSE
Requires-Dist: spacy>=3.7.0
Requires-Dist: fuzzywuzzy
Requires-Dist: ru_cv_parse_model
